ttictoc/__init__.py
ttictoc/tictoc.py
ttictoc-0.5.6.dist-info/LICENSE
ttictoc-0.5.6.dist-info/METADATA
ttictoc-0.5.6.dist-info/WHEEL
ttictoc-0.5.6.dist-info/top_level.txt
ttictoc-0.5.6.dist-info/zip-safe
ttictoc-0.5.6.dist-info/RECORD
