Metadata-Version: 2.1
Name: ttictoc
Version: 0.5.6
Summary: Time parts of your code easily.
Home-page: https://github.com/hector-sab/ttictoc
Author: Hector Sanchez
Author-email: hector.direct@gmail.com
License: MIT
Keywords: tictoc tic toc time timing
Platform: UNKNOWN
Classifier: Programming Language :: Python
Classifier: Programming Language :: Python :: 2.7
Classifier: Programming Language :: Python :: 3
Classifier: Programming Language :: Python :: 3.3
Classifier: Programming Language :: Python :: 3.4
Classifier: Programming Language :: Python :: 3.5
Classifier: Programming Language :: Python :: 3.6
Classifier: License :: OSI Approved :: MIT License
Classifier: Operating System :: OS Independent
